unitycatalog_migrate/__init__.py
unitycatalog_migrate/coro.py
unitycatalog_migrate/main.py
unitycatalog_migrate/output.py
unitycatalog_migrate/py.typed
unitycatalog_migrate/uc.py
unitycatalog_migrate-0.1.1.dist-info/METADATA
unitycatalog_migrate-0.1.1.dist-info/WHEEL
unitycatalog_migrate-0.1.1.dist-info/entry_points.txt
unitycatalog_migrate-0.1.1.dist-info/licenses/LICENSE
unitycatalog_migrate-0.1.1.dist-info/RECORD
