Metadata-Version: 2.4
Name: unitycatalog-migrate
Version: 0.1.1
Summary: Migrate catalogs from Databricks to Unity Catalog
Author-email: Daniël Tom <d.e.tom89@gmail.com>
License: MIT License
License-File: LICENSE
Keywords: databricks,migration,unitycatalog
Classifier: Development Status :: 5 - Production/Stable
Classifier: Intended Audience :: Developers
Classifier: License :: OSI Approved :: MIT License
Classifier: Programming Language :: Python
Classifier: Programming Language :: Python :: 3
Classifier: Programming Language :: Python :: 3.9
Classifier: Programming Language :: Python :: 3.10
Classifier: Programming Language :: Python :: 3.11
Classifier: Programming Language :: Python :: 3.12
Classifier: Programming Language :: Python :: 3.13
Classifier: Topic :: Software Development :: Libraries :: Python Modules
Requires-Python: >=3.9
Requires-Dist: databricks-sdk>=0.41.0
Requires-Dist: typer>=0.15.1
Requires-Dist: unitycatalog-client>=0.2.1
